[
  {
    "id": 1,
    "planet_name": "Earth",
    "distance_from_sun": "93 million miles",
    "diameter": "7,917.5 miles",
    "planet_images": [
      "/public/images/earth.jpg"
    ]
  },
  {
    "id": 2,
    "planet_name": "Mars",
    "distance_from_sun": "142 million miles",
    "diameter": "4,212 miles",
    "planet_images": [
      "/public/images/earth.jpg"
    ]
  },
  {
    "id": 3,
    "planet_name": "Jupiter",
    "distance_from_sun": "484 million miles",
    "diameter": "86,881.4 miles",
    "planet_images": [
      "/public/images/earth.jpg"
    ]
  },
  {
    "id": 4,
    "planet_name": "Uranus",
    "distance_from_sun": "890 million miles",
    "diameter": "72,366 miles",
    "planet_images": [
      "/public/images/earth.jpg",
      "/public/images/earth.jpg"
    ]
  },
  {
    "id": 5,
    "planet_name": "Mercury",
    "distance_from_sun": "13 million miles",
    "diameter": "7,917.5 miles",
    "planet_images": [
      "/public/images/earth.jpg"
    ]
  }
]